source_sftp_bulk/__init__.py
source_sftp_bulk/client.py
source_sftp_bulk/run.py
source_sftp_bulk/source.py
source_sftp_bulk/spec.py
source_sftp_bulk/stream_reader.py
airbyte_source_sftp_bulk-1.9.0.dist-info/METADATA
airbyte_source_sftp_bulk-1.9.0.dist-info/WHEEL
airbyte_source_sftp_bulk-1.9.0.dist-info/entry_points.txt
airbyte_source_sftp_bulk-1.9.0.dist-info/RECORD
