Metadata-Version: 2.1
Name: airbyte-source-sftp-bulk
Version: 1.9.0
Summary: Source implementation for SFTP Bulk.
Home-page: https://airbyte.com
License: ELv2
Author: Airbyte
Author-email: contact@airbyte.io
Requires-Python: >=3.10,<3.12
Classifier: License :: Other/Proprietary License
Classifier: Programming Language :: Python :: 3
Classifier: Programming Language :: Python :: 3.10
Classifier: Programming Language :: Python :: 3.11
Requires-Dist: airbyte-cdk[file-based] (>=7.0.4,<8.0.0)
Requires-Dist: paramiko (==3.4.0)
Requires-Dist: psutil (==6.1.0)
Project-URL: Documentation, https://docs.airbyte.com/integrations/sources/sftp-bulk
Project-URL: Repository, https://github.com/airbytehq/airbyte
